pyroscope_beta-0.3.1.data/purelib/pyroscope_beta/__init__.py
pyroscope_beta-0.3.1.data/purelib/pyroscope_beta/_native.py
pyroscope_beta-0.3.1.data/purelib/pyroscope_beta/_native__ffi.py
pyroscope_beta-0.3.1.data/purelib/pyroscope_beta/_native__lib.cpython-39-darwin.so
pyroscope_beta-0.3.1.dist-info/LICENSE
pyroscope_beta-0.3.1.dist-info/METADATA
pyroscope_beta-0.3.1.dist-info/WHEEL
pyroscope_beta-0.3.1.dist-info/top_level.txt
pyroscope_beta-0.3.1.dist-info/RECORD
